{
  "practice-exam-1.md": [
    {
      "num": "1",
      "slides": [
        1,
        3,
        5,
        10,
        11,
        14
      ]
    },
    {
      "num": "2",
      "slides": [
        22,
        23,
        24,
        50,
        51
      ]
    },
    {
      "num": "3",
      "slides": [
        1,
        3,
        5,
        14,
        15,
        30
      ]
    },
    {
      "num": "4",
      "slides": [
        23,
        26,
        29,
        61,
        64,
        65
      ]
    },
    {
      "num": "5",
      "slides": [
        37,
        38,
        39
      ]
    },
    {
      "num": "6",
      "slides": [
        1,
        3,
        5,
        26,
        27,
        30
      ]
    },
    {
      "num": "7",
      "slides": [
        253,
        255,
        257,
        549,
        551
      ]
    },
    {
      "num": "8",
      "slides": [
        1,
        3,
        5,
        61,
        64,
        67
      ]
    },
    {
      "num": "9",
      "slides": [
        341,
        344,
        347,
        355,
        357,
        359
      ]
    },
    {
      "num": "10",
      "slides": [
        341,
        344,
        347,
        355,
        357,
        359
      ]
    },
    {
      "num": "11",
      "slides": [
        357,
        359,
        363,
        365,
        367,
        401
      ]
    },
    {
      "num": "12",
      "slides": [
        50,
        51,
        787,
        789,
        791
      ]
    },
    {
      "num": "13",
      "slides": [
        781,
        784,
        787,
        789,
        791,
        793
      ]
    },
    {
      "num": "14",
      "slides": [
        355,
        357,
        359,
        401,
        403,
        405
      ]
    },
    {
      "num": "15",
      "slides": [
        341,
        344,
        347,
        355,
        357,
        359
      ]
    },
    {
      "num": "16",
      "slides": [
        50,
        51,
        781,
        784,
        787,
        789
      ]
    },
    {
      "num": "17",
      "slides": [
        50,
        51,
        781,
        784,
        787
      ]
    },
    {
      "num": "18",
      "slides": [
        1,
        3,
        5,
        14,
        15,
        22
      ]
    }
  ],
  "practice-exam-10.md": [
    {
      "num": "1",
      "slides": []
    },
    {
      "num": "2",
      "slides": []
    },
    {
      "num": "3",
      "slides": [
        401,
        403,
        405
      ]
    },
    {
      "num": "4",
      "slides": [
        401,
        403,
        405
      ]
    },
    {
      "num": "5",
      "slides": [
        401,
        403,
        405
      ]
    },
    {
      "num": "6",
      "slides": [
        401,
        403,
        405
      ]
    },
    {
      "num": "7",
      "slides": [
        413,
        415,
        417,
        419,
        421
      ]
    },
    {
      "num": "8",
      "slides": [
        355,
        357,
        359,
        401,
        403,
        405
      ]
    },
    {
      "num": "9",
      "slides": [
        401,
        403,
        405,
        413,
        415,
        417
      ]
    },
    {
      "num": "10",
      "slides": [
        341,
        344,
        347,
        413,
        415,
        419
      ]
    },
    {
      "num": "11",
      "slides": [
        401,
        403,
        405
      ]
    },
    {
      "num": "12",
      "slides": [
        355,
        357,
        359
      ]
    },
    {
      "num": "13",
      "slides": [
        401,
        403,
        405
      ]
    },
    {
      "num": "14",
      "slides": [
        401,
        403,
        405,
        621,
        623,
        625
      ]
    },
    {
      "num": "15",
      "slides": [
        341,
        344,
        347,
        355,
        357,
        359
      ]
    }
  ],
  "practice-exam-11.md": [
    {
      "num": "1",
      "slides": [
        355,
        357,
        359,
        363,
        365,
        367
      ]
    },
    {
      "num": "2",
      "slides": [
        341,
        344,
        347,
        355,
        357,
        359
      ]
    },
    {
      "num": "3",
      "slides": [
        485,
        487,
        489
      ]
    },
    {
      "num": "4",
      "slides": [
        341,
        344,
        347,
        355,
        357,
        359
      ]
    },
    {
      "num": "5",
      "slides": [
        341,
        344,
        347,
        491,
        493,
        495
      ]
    },
    {
      "num": "6",
      "slides": [
        355,
        357,
        359,
        491,
        493,
        495
      ]
    },
    {
      "num": "7",
      "slides": [
        341,
        344,
        347,
        355,
        357,
        359
      ]
    },
    {
      "num": "8",
      "slides": [
        341,
        344,
        347,
        355,
        357,
        359
      ]
    },
    {
      "num": "9",
      "slides": [
        355,
        357,
        359,
        497,
        499,
        501
      ]
    },
    {
      "num": "10",
      "slides": [
        355,
        357,
        359,
        413,
        415
      ]
    },
    {
      "num": "11",
      "slides": [
        341,
        344,
        347,
        355,
        357,
        359
      ]
    },
    {
      "num": "12",
      "slides": [
        413,
        415,
        507,
        509
      ]
    },
    {
      "num": "13",
      "slides": [
        355,
        357,
        359,
        509,
        511,
        513
      ]
    },
    {
      "num": "14",
      "slides": [
        341,
        344,
        347,
        515,
        517,
        621
      ]
    },
    {
      "num": "15",
      "slides": [
        341,
        344,
        347,
        517,
        519,
        521
      ]
    },
    {
      "num": "16",
      "slides": [
        517,
        519,
        521
      ]
    },
    {
      "num": "17",
      "slides": [
        341,
        344,
        347,
        517,
        519,
        521
      ]
    },
    {
      "num": "18",
      "slides": [
        66,
        68,
        70,
        271,
        274,
        277
      ]
    }
  ],
  "practice-exam-12.md": [
    {
      "num": "1",
      "slides": [
        66,
        68,
        70,
        781,
        784,
        787
      ]
    },
    {
      "num": "2",
      "slides": [
        50,
        51,
        355,
        357,
        359,
        781
      ]
    },
    {
      "num": "3",
      "slides": [
        781,
        784,
        787,
        793,
        795
      ]
    },
    {
      "num": "4",
      "slides": [
        341,
        344,
        347,
        781,
        784,
        787
      ]
    },
    {
      "num": "5",
      "slides": [
        781,
        784,
        787,
        797,
        799,
        801
      ]
    },
    {
      "num": "6",
      "slides": [
        50,
        51,
        355,
        357,
        359,
        781
      ]
    },
    {
      "num": "7",
      "slides": [
        50,
        51,
        355,
        357,
        359,
        781
      ]
    },
    {
      "num": "8",
      "slides": [
        50,
        51,
        355,
        357,
        359,
        781
      ]
    },
    {
      "num": "9",
      "slides": [
        355,
        357,
        359,
        781,
        784,
        787
      ]
    },
    {
      "num": "10",
      "slides": [
        50,
        51,
        355,
        357,
        359,
        781
      ]
    },
    {
      "num": "11",
      "slides": [
        310,
        313,
        781,
        784,
        787,
        793
      ]
    },
    {
      "num": "12",
      "slides": [
        341,
        344,
        347,
        815,
        817,
        819
      ]
    },
    {
      "num": "13",
      "slides": [
        363,
        365,
        367,
        781,
        784,
        787
      ]
    },
    {
      "num": "14",
      "slides": [
        781,
        784,
        787,
        789,
        791
      ]
    },
    {
      "num": "15",
      "slides": [
        50,
        51,
        781,
        784,
        787,
        793
      ]
    },
    {
      "num": "16",
      "slides": [
        355,
        357,
        359,
        781,
        784,
        787
      ]
    },
    {
      "num": "17",
      "slides": [
        355,
        357,
        359,
        781,
        784,
        787
      ]
    },
    {
      "num": "18",
      "slides": [
        32,
        35,
        38,
        50,
        51,
        66
      ]
    }
  ],
  "practice-exam-13.md": [
    {
      "num": "1",
      "slides": [
        32,
        35,
        38
      ]
    },
    {
      "num": "2",
      "slides": [
        32,
        35,
        38
      ]
    },
    {
      "num": "3",
      "slides": [
        32,
        35,
        38
      ]
    },
    {
      "num": "4",
      "slides": [
        32,
        35,
        38,
        50,
        51,
        355
      ]
    },
    {
      "num": "5",
      "slides": [
        32,
        35,
        38
      ]
    },
    {
      "num": "6",
      "slides": [
        32,
        35,
        38,
        66,
        68,
        70
      ]
    },
    {
      "num": "7",
      "slides": [
        23,
        26,
        29
      ]
    },
    {
      "num": "8",
      "slides": [
        23,
        26,
        29
      ]
    },
    {
      "num": "9",
      "slides": [
        23,
        26,
        29
      ]
    },
    {
      "num": "10",
      "slides": [
        23,
        26,
        29,
        549,
        551
      ]
    },
    {
      "num": "11",
      "slides": [
        23,
        26,
        29,
        355,
        357,
        359
      ]
    },
    {
      "num": "12",
      "slides": [
        23,
        26,
        29
      ]
    },
    {
      "num": "13",
      "slides": [
        23,
        26,
        29
      ]
    },
    {
      "num": "14",
      "slides": [
        32,
        35,
        38,
        100,
        103,
        106
      ]
    },
    {
      "num": "15",
      "slides": [
        23,
        26,
        29,
        32,
        35,
        38
      ]
    }
  ],
  "practice-exam-14.md": [
    {
      "num": "1",
      "slides": [
        50,
        51,
        355,
        357,
        359,
        663
      ]
    },
    {
      "num": "2",
      "slides": [
        401,
        403,
        405,
        641,
        644,
        645
      ]
    },
    {
      "num": "3",
      "slides": [
        401,
        403,
        405,
        645,
        647,
        659
      ]
    },
    {
      "num": "4",
      "slides": [
        641,
        644,
        647,
        659,
        661,
        815
      ]
    },
    {
      "num": "5",
      "slides": [
        355,
        357,
        359,
        401,
        403,
        405
      ]
    },
    {
      "num": "6",
      "slides": [
        401,
        403,
        405,
        641,
        644,
        645
      ]
    },
    {
      "num": "7",
      "slides": [
        341,
        344,
        347,
        641,
        644,
        647
      ]
    },
    {
      "num": "8",
      "slides": [
        355,
        357,
        359,
        621,
        623,
        625
      ]
    },
    {
      "num": "9",
      "slides": [
        641,
        644,
        647,
        649,
        651,
        653
      ]
    },
    {
      "num": "10",
      "slides": [
        355,
        357,
        359,
        621,
        623,
        625
      ]
    },
    {
      "num": "11",
      "slides": [
        341,
        344,
        347,
        355,
        357,
        359
      ]
    },
    {
      "num": "12",
      "slides": [
        341,
        344,
        347,
        401,
        403,
        405
      ]
    },
    {
      "num": "13",
      "slides": [
        355,
        357,
        359,
        641,
        643
      ]
    },
    {
      "num": "14",
      "slides": [
        641,
        643
      ]
    },
    {
      "num": "15",
      "slides": [
        641,
        643,
        644,
        647,
        685,
        688
      ]
    },
    {
      "num": "16",
      "slides": [
        621,
        623,
        625,
        641,
        643,
        644
      ]
    },
    {
      "num": "17",
      "slides": []
    },
    {
      "num": "18",
      "slides": [
        641,
        644,
        647,
        685,
        688,
        691
      ]
    },
    {
      "num": "1",
      "slides": [
        355,
        357,
        359,
        645,
        647,
        815
      ]
    },
    {
      "num": "2",
      "slides": [
        621,
        623,
        625,
        645,
        647,
        649
      ]
    },
    {
      "num": "3",
      "slides": [
        645,
        647,
        663,
        665,
        667
      ]
    },
    {
      "num": "4",
      "slides": [
        641,
        644,
        647,
        659,
        661
      ]
    },
    {
      "num": "5",
      "slides": [
        341,
        344,
        347,
        355,
        357,
        359
      ]
    },
    {
      "num": "6",
      "slides": [
        355,
        357,
        359,
        659,
        661,
        815
      ]
    },
    {
      "num": "7",
      "slides": [
        341,
        344,
        347,
        355,
        357,
        359
      ]
    },
    {
      "num": "8",
      "slides": [
        355,
        357,
        359,
        401,
        403,
        405
      ]
    },
    {
      "num": "9",
      "slides": [
        341,
        344,
        347,
        401,
        403,
        405
      ]
    },
    {
      "num": "10",
      "slides": [
        641,
        644,
        645,
        647,
        663,
        665
      ]
    },
    {
      "num": "11",
      "slides": [
        341,
        344,
        347,
        355,
        357,
        359
      ]
    },
    {
      "num": "12",
      "slides": [
        341,
        344,
        347,
        641,
        644,
        645
      ]
    },
    {
      "num": "13",
      "slides": [
        355,
        357,
        359,
        643
      ]
    },
    {
      "num": "14",
      "slides": [
        641,
        643
      ]
    },
    {
      "num": "15",
      "slides": [
        621,
        623,
        625,
        641,
        643
      ]
    },
    {
      "num": "16",
      "slides": [
        196,
        200,
        204,
        621,
        623,
        625
      ]
    },
    {
      "num": "17",
      "slides": [
        106,
        641,
        643,
        644,
        647,
        663
      ]
    },
    {
      "num": "18",
      "slides": [
        641,
        644,
        647,
        685,
        688,
        691
      ]
    }
  ],
  "practice-exam-15.md": [
    {
      "num": "1",
      "slides": [
        401,
        403,
        405
      ]
    },
    {
      "num": "2",
      "slides": [
        355,
        357,
        359,
        401,
        403,
        405
      ]
    },
    {
      "num": "3",
      "slides": [
        355,
        357,
        359,
        401,
        403,
        405
      ]
    },
    {
      "num": "4",
      "slides": [
        401,
        403,
        405
      ]
    },
    {
      "num": "5",
      "slides": [
        417,
        419
      ]
    },
    {
      "num": "6",
      "slides": []
    },
    {
      "num": "7",
      "slides": [
        401,
        403,
        405
      ]
    },
    {
      "num": "8",
      "slides": [
        341,
        344,
        347,
        401,
        403,
        405
      ]
    },
    {
      "num": "9",
      "slides": [
        341,
        344,
        347,
        401,
        403,
        405
      ]
    },
    {
      "num": "10",
      "slides": [
        355,
        357,
        359,
        401,
        403,
        405
      ]
    },
    {
      "num": "11",
      "slides": [
        196,
        200,
        204,
        271,
        274,
        277
      ]
    },
    {
      "num": "12",
      "slides": []
    },
    {
      "num": "13",
      "slides": [
        501,
        504,
        507
      ]
    },
    {
      "num": "14",
      "slides": [
        501,
        504,
        507
      ]
    },
    {
      "num": "15",
      "slides": [
        196,
        200,
        204,
        271,
        274,
        277
      ]
    }
  ],
  "practice-exam-2.md": [
    {
      "num": "1",
      "slides": [
        271,
        274,
        277
      ]
    },
    {
      "num": "2",
      "slides": []
    },
    {
      "num": "3",
      "slides": [
        271,
        274,
        277,
        621,
        623,
        625
      ]
    },
    {
      "num": "4",
      "slides": [
        32,
        35,
        38,
        301,
        304,
        641
      ]
    },
    {
      "num": "5",
      "slides": []
    },
    {
      "num": "6",
      "slides": [
        355,
        357,
        359,
        621,
        623,
        625
      ]
    },
    {
      "num": "7",
      "slides": [
        355,
        357,
        359
      ]
    },
    {
      "num": "8",
      "slides": [
        517,
        519,
        521,
        641,
        644,
        645
      ]
    },
    {
      "num": "9",
      "slides": [
        32,
        35,
        38,
        641,
        643,
        644
      ]
    },
    {
      "num": "10",
      "slides": [
        641,
        643,
        644,
        645,
        647
      ]
    },
    {
      "num": "11",
      "slides": [
        355,
        357,
        359,
        501,
        504,
        507
      ]
    },
    {
      "num": "12",
      "slides": [
        501,
        504,
        507,
        563,
        565,
        567
      ]
    },
    {
      "num": "13",
      "slides": [
        307,
        310,
        313,
        563,
        565,
        567
      ]
    },
    {
      "num": "14",
      "slides": [
        501,
        504,
        507,
        541,
        543,
        573
      ]
    },
    {
      "num": "15",
      "slides": [
        501,
        504,
        507,
        561,
        563,
        565
      ]
    },
    {
      "num": "16",
      "slides": [
        561,
        563,
        573,
        575,
        577,
        601
      ]
    },
    {
      "num": "17",
      "slides": [
        501,
        504,
        507,
        561,
        563,
        601
      ]
    },
    {
      "num": "18",
      "slides": [
        621,
        623,
        625,
        731,
        733,
        735
      ]
    },
    {
      "num": "19",
      "slides": [
        621,
        623,
        625,
        731,
        733,
        735
      ]
    },
    {
      "num": "20",
      "slides": [
        196,
        200,
        204,
        271,
        274,
        277
      ]
    }
  ],
  "practice-exam-3.md": [
    {
      "num": "1",
      "slides": [
        341,
        344,
        347,
        355,
        357,
        359
      ]
    },
    {
      "num": "2",
      "slides": [
        341,
        344,
        347,
        355,
        357,
        359
      ]
    },
    {
      "num": "3",
      "slides": [
        355,
        357,
        359,
        361
      ]
    },
    {
      "num": "4",
      "slides": [
        355,
        357,
        359,
        641,
        644,
        647
      ]
    },
    {
      "num": "5",
      "slides": [
        341,
        344,
        347,
        641,
        644,
        645
      ]
    },
    {
      "num": "6",
      "slides": [
        355,
        357,
        359,
        401,
        403,
        405
      ]
    },
    {
      "num": "7",
      "slides": [
        641,
        644,
        645,
        647
      ]
    },
    {
      "num": "8",
      "slides": [
        401,
        403,
        405,
        641,
        643,
        644
      ]
    },
    {
      "num": "9",
      "slides": [
        781,
        783,
        785
      ]
    },
    {
      "num": "10",
      "slides": [
        781,
        783,
        785
      ]
    },
    {
      "num": "11",
      "slides": [
        781,
        783,
        785
      ]
    },
    {
      "num": "12",
      "slides": [
        283,
        286,
        355,
        357,
        359,
        781
      ]
    },
    {
      "num": "13",
      "slides": [
        271,
        274,
        277,
        283,
        286
      ]
    },
    {
      "num": "14",
      "slides": [
        271,
        274,
        277,
        289,
        292,
        809
      ]
    },
    {
      "num": "15",
      "slides": [
        271,
        274,
        277,
        301,
        304,
        341
      ]
    },
    {
      "num": "16",
      "slides": [
        295
      ]
    },
    {
      "num": "17",
      "slides": [
        271,
        274,
        277,
        289,
        292,
        815
      ]
    },
    {
      "num": "18",
      "slides": [
        621,
        623,
        625,
        815,
        817,
        819
      ]
    },
    {
      "num": "19",
      "slides": [
        50,
        51,
        781,
        784,
        787,
        789
      ]
    },
    {
      "num": "20",
      "slides": [
        50,
        51,
        56,
        57,
        59,
        196
      ]
    }
  ],
  "practice-exam-4.md": [
    {
      "num": "1",
      "slides": [
        253
      ]
    },
    {
      "num": "2",
      "slides": [
        257
      ]
    },
    {
      "num": "3",
      "slides": [
        257
      ]
    },
    {
      "num": "4",
      "slides": [
        258
      ]
    },
    {
      "num": "5",
      "slides": [
        254,
        255
      ]
    },
    {
      "num": "6",
      "slides": [
        243
      ]
    },
    {
      "num": "7",
      "slides": [
        243
      ]
    },
    {
      "num": "8",
      "slides": [
        246
      ]
    },
    {
      "num": "9",
      "slides": [
        248,
        249,
        250
      ]
    },
    {
      "num": "10",
      "slides": [
        251
      ]
    },
    {
      "num": "11",
      "slides": [
        260
      ]
    },
    {
      "num": "12",
      "slides": [
        261
      ]
    },
    {
      "num": "13",
      "slides": [
        262
      ]
    },
    {
      "num": "14",
      "slides": [
        341,
        342,
        343
      ]
    },
    {
      "num": "15",
      "slides": [
        344
      ]
    },
    {
      "num": "16",
      "slides": [
        377,
        378
      ]
    },
    {
      "num": "17",
      "slides": [
        361
      ]
    },
    {
      "num": "18",
      "slides": [
        364,
        365
      ]
    },
    {
      "num": "19",
      "slides": [
        380,
        381
      ]
    },
    {
      "num": "20",
      "slides": [
        379
      ]
    },
    {
      "num": "1",
      "slides": [
        253
      ]
    },
    {
      "num": "2",
      "slides": [
        257
      ]
    },
    {
      "num": "3",
      "slides": [
        257
      ]
    },
    {
      "num": "4",
      "slides": [
        258
      ]
    },
    {
      "num": "5",
      "slides": [
        254,
        255
      ]
    },
    {
      "num": "6",
      "slides": [
        243
      ]
    },
    {
      "num": "7",
      "slides": [
        243
      ]
    },
    {
      "num": "8",
      "slides": [
        246
      ]
    },
    {
      "num": "9",
      "slides": [
        248
      ]
    },
    {
      "num": "10",
      "slides": [
        251
      ]
    },
    {
      "num": "11",
      "slides": [
        260
      ]
    },
    {
      "num": "12",
      "slides": [
        261
      ]
    },
    {
      "num": "13",
      "slides": [
        262
      ]
    },
    {
      "num": "14",
      "slides": [
        341,
        342,
        343
      ]
    },
    {
      "num": "15",
      "slides": [
        344
      ]
    },
    {
      "num": "16",
      "slides": [
        377,
        378
      ]
    },
    {
      "num": "17",
      "slides": [
        345,
        361
      ]
    },
    {
      "num": "18",
      "slides": [
        364,
        365
      ]
    },
    {
      "num": "19",
      "slides": [
        380,
        381
      ]
    },
    {
      "num": "20",
      "slides": [
        379
      ]
    }
  ],
  "practice-exam-5.md": [
    {
      "num": "1",
      "slides": [
        431,
        433,
        435
      ]
    },
    {
      "num": "2",
      "slides": [
        431,
        433,
        435
      ]
    },
    {
      "num": "3",
      "slides": [
        431,
        433,
        435
      ]
    },
    {
      "num": "4",
      "slides": [
        431,
        433,
        435,
        621,
        623,
        625
      ]
    },
    {
      "num": "5",
      "slides": [
        431,
        433,
        435
      ]
    },
    {
      "num": "6",
      "slides": [
        431,
        433,
        435,
        815,
        817,
        819
      ]
    },
    {
      "num": "7",
      "slides": [
        455,
        456,
        457,
        458,
        459
      ]
    },
    {
      "num": "8",
      "slides": [
        355,
        357,
        359,
        455,
        457,
        459
      ]
    },
    {
      "num": "9",
      "slides": []
    },
    {
      "num": "10",
      "slides": [
        455,
        457,
        459
      ]
    },
    {
      "num": "11",
      "slides": [
        431,
        433,
        435,
        455,
        457,
        459
      ]
    },
    {
      "num": "12",
      "slides": [
        620,
        621,
        622,
        623,
        624
      ]
    },
    {
      "num": "13",
      "slides": [
        621,
        623,
        625
      ]
    },
    {
      "num": "14",
      "slides": [
        307,
        310,
        313,
        623,
        625
      ]
    },
    {
      "num": "15",
      "slides": [
        629,
        631,
        633
      ]
    },
    {
      "num": "16",
      "slides": [
        621,
        623,
        625,
        629,
        631,
        633
      ]
    },
    {
      "num": "17",
      "slides": [
        635,
        637
      ]
    },
    {
      "num": "18",
      "slides": [
        637,
        639
      ]
    },
    {
      "num": "19",
      "slides": []
    },
    {
      "num": "20",
      "slides": [
        430,
        432,
        433,
        435,
        436,
        437
      ]
    }
  ],
  "practice-exam-6.md": [
    {
      "num": "1",
      "slides": [
        525,
        526,
        527,
        528,
        529
      ]
    },
    {
      "num": "2",
      "slides": [
        540
      ]
    },
    {
      "num": "3",
      "slides": [
        541,
        542
      ]
    },
    {
      "num": "4",
      "slides": [
        543,
        544,
        545,
        546
      ]
    },
    {
      "num": "5",
      "slides": [
        548,
        549,
        550,
        551,
        552
      ]
    },
    {
      "num": "6",
      "slides": [
        554,
        555,
        556,
        557
      ]
    },
    {
      "num": "7",
      "slides": [
        640,
        641,
        642,
        643,
        644
      ]
    },
    {
      "num": "8",
      "slides": [
        645,
        646,
        647,
        648,
        649
      ]
    },
    {
      "num": "9",
      "slides": [
        645,
        646,
        647,
        648,
        649
      ]
    },
    {
      "num": "10",
      "slides": [
        655,
        656,
        657,
        658,
        659
      ]
    },
    {
      "num": "11",
      "slides": [
        196,
        200,
        204,
        401,
        403,
        405
      ]
    },
    {
      "num": "12",
      "slides": [
        640,
        641,
        642,
        643,
        644
      ]
    },
    {
      "num": "13",
      "slides": [
        645,
        646,
        647,
        648,
        649
      ]
    },
    {
      "num": "14",
      "slides": [
        685,
        686,
        687,
        688,
        689
      ]
    },
    {
      "num": "15",
      "slides": [
        685,
        686,
        687,
        688,
        689
      ]
    },
    {
      "num": "16",
      "slides": [
        690,
        691,
        692,
        693,
        694
      ]
    },
    {
      "num": "17",
      "slides": [
        690,
        691,
        692,
        693,
        694
      ]
    },
    {
      "num": "18",
      "slides": [
        560,
        561,
        562,
        563,
        564
      ]
    },
    {
      "num": "19",
      "slides": [
        575,
        576,
        577,
        578,
        579
      ]
    },
    {
      "num": "20",
      "slides": [
        100,
        103,
        106,
        196,
        200,
        204
      ]
    }
  ],
  "practice-exam-7.md": [
    {
      "num": "1",
      "slides": [
        271,
        274,
        277
      ]
    },
    {
      "num": "2",
      "slides": [
        271,
        274,
        277
      ]
    },
    {
      "num": "3",
      "slides": [
        277,
        280,
        283
      ]
    },
    {
      "num": "4",
      "slides": [
        271,
        274,
        277
      ]
    },
    {
      "num": "5",
      "slides": []
    },
    {
      "num": "6",
      "slides": [
        289,
        292
      ]
    },
    {
      "num": "7",
      "slides": [
        277,
        280,
        283,
        289,
        292,
        295
      ]
    },
    {
      "num": "8",
      "slides": [
        295,
        298
      ]
    },
    {
      "num": "9",
      "slides": []
    },
    {
      "num": "10",
      "slides": [
        271,
        274,
        277,
        298,
        301
      ]
    },
    {
      "num": "11",
      "slides": [
        277,
        280,
        283,
        295,
        298
      ]
    },
    {
      "num": "12",
      "slides": [
        196,
        200,
        204,
        271,
        274,
        277
      ]
    },
    {
      "num": "13",
      "slides": [
        196,
        200,
        204,
        271,
        274,
        277
      ]
    },
    {
      "num": "14",
      "slides": []
    },
    {
      "num": "15",
      "slides": [
        277,
        280
      ]
    },
    {
      "num": "16",
      "slides": []
    },
    {
      "num": "17",
      "slides": [
        307,
        310,
        313,
        341,
        344,
        347
      ]
    },
    {
      "num": "18",
      "slides": [
        310,
        313,
        341,
        344,
        347,
        621
      ]
    },
    {
      "num": "19",
      "slides": [
        289,
        292,
        341,
        344,
        347
      ]
    },
    {
      "num": "20",
      "slides": [
        307,
        310,
        313,
        355,
        357,
        359
      ]
    },
    {
      "num": "21",
      "slides": [
        310,
        313,
        735
      ]
    },
    {
      "num": "1",
      "slides": [
        271,
        274,
        277
      ]
    },
    {
      "num": "2",
      "slides": [
        277,
        280
      ]
    },
    {
      "num": "3",
      "slides": [
        277,
        280,
        355,
        357,
        359
      ]
    },
    {
      "num": "4",
      "slides": []
    },
    {
      "num": "5",
      "slides": []
    },
    {
      "num": "6",
      "slides": [
        289,
        292
      ]
    },
    {
      "num": "7",
      "slides": [
        277,
        280,
        283,
        289,
        292,
        295
      ]
    },
    {
      "num": "8",
      "slides": [
        295,
        298
      ]
    },
    {
      "num": "9",
      "slides": [
        277,
        280
      ]
    },
    {
      "num": "10",
      "slides": [
        271,
        274,
        277,
        280,
        283,
        298
      ]
    },
    {
      "num": "11",
      "slides": []
    },
    {
      "num": "12",
      "slides": [
        196,
        200,
        204,
        277,
        280,
        283
      ]
    },
    {
      "num": "13",
      "slides": [
        196,
        200,
        204,
        271,
        274,
        277
      ]
    },
    {
      "num": "14",
      "slides": []
    },
    {
      "num": "15",
      "slides": [
        277,
        280
      ]
    },
    {
      "num": "16",
      "slides": []
    },
    {
      "num": "17",
      "slides": [
        307,
        310,
        313,
        341,
        344,
        347
      ]
    },
    {
      "num": "18",
      "slides": [
        310,
        313,
        341,
        344,
        347,
        735
      ]
    },
    {
      "num": "19",
      "slides": [
        271,
        274,
        277,
        289,
        292,
        341
      ]
    },
    {
      "num": "20",
      "slides": [
        307,
        310,
        313,
        319,
        322,
        735
      ]
    },
    {
      "num": "21",
      "slides": [
        271,
        274,
        277,
        310,
        313,
        735
      ]
    }
  ],
  "practice-exam-8.md": [
    {
      "num": "1",
      "slides": [
        563,
        565,
        567,
        573,
        575,
        577
      ]
    },
    {
      "num": "2",
      "slides": [
        355,
        357,
        359,
        563,
        565,
        567
      ]
    },
    {
      "num": "3",
      "slides": [
        501,
        504,
        507
      ]
    },
    {
      "num": "4",
      "slides": [
        563,
        565,
        567,
        573,
        575,
        577
      ]
    },
    {
      "num": "5",
      "slides": [
        563,
        565,
        567,
        815,
        817,
        819
      ]
    },
    {
      "num": "6",
      "slides": [
        563,
        565,
        567,
        815,
        817,
        819
      ]
    },
    {
      "num": "7",
      "slides": [
        355,
        357,
        359,
        555,
        557,
        563
      ]
    },
    {
      "num": "8",
      "slides": [
        815,
        817,
        819
      ]
    },
    {
      "num": "9",
      "slides": [
        815,
        817,
        819
      ]
    },
    {
      "num": "10",
      "slides": [
        601,
        603,
        605
      ]
    },
    {
      "num": "11",
      "slides": [
        573,
        575,
        577,
        601,
        603,
        605
      ]
    },
    {
      "num": "12",
      "slides": [
        355,
        357,
        359,
        573,
        575,
        577
      ]
    },
    {
      "num": "13",
      "slides": [
        601,
        603,
        605
      ]
    },
    {
      "num": "14",
      "slides": [
        66,
        68,
        70,
        355,
        357,
        359
      ]
    },
    {
      "num": "15",
      "slides": [
        501,
        504,
        507
      ]
    },
    {
      "num": "16",
      "slides": []
    },
    {
      "num": "17",
      "slides": [
        307,
        310,
        313,
        501,
        504,
        507
      ]
    },
    {
      "num": "18",
      "slides": [
        733,
        735
      ]
    },
    {
      "num": "19",
      "slides": [
        501,
        504,
        507,
        761,
        763
      ]
    },
    {
      "num": "20",
      "slides": [
        543,
        545,
        547,
        767,
        769
      ]
    },
    {
      "num": "21",
      "slides": []
    },
    {
      "num": "22",
      "slides": [
        641,
        644,
        645,
        647,
        649,
        651
      ]
    },
    {
      "num": "1",
      "slides": [
        66,
        68,
        70,
        563,
        565,
        567
      ]
    },
    {
      "num": "2",
      "slides": [
        307,
        310,
        313,
        563,
        565,
        567
      ]
    },
    {
      "num": "3",
      "slides": [
        563,
        565,
        567,
        573,
        575,
        577
      ]
    },
    {
      "num": "4",
      "slides": [
        563,
        565,
        567,
        573,
        575,
        577
      ]
    },
    {
      "num": "5",
      "slides": [
        815,
        817,
        819
      ]
    },
    {
      "num": "6",
      "slides": [
        815,
        817,
        819
      ]
    },
    {
      "num": "7",
      "slides": [
        355,
        357,
        359,
        563,
        565,
        567
      ]
    },
    {
      "num": "8",
      "slides": [
        815,
        817,
        819
      ]
    },
    {
      "num": "9",
      "slides": []
    },
    {
      "num": "10",
      "slides": [
        563,
        565,
        567,
        573,
        575,
        577
      ]
    },
    {
      "num": "11",
      "slides": [
        563,
        565,
        567,
        573,
        575,
        577
      ]
    },
    {
      "num": "12",
      "slides": [
        573,
        575,
        577,
        601,
        603,
        605
      ]
    },
    {
      "num": "13",
      "slides": [
        66,
        68,
        70,
        601,
        603,
        605
      ]
    },
    {
      "num": "14",
      "slides": [
        66,
        68,
        70,
        607,
        609
      ]
    },
    {
      "num": "15",
      "slides": [
        501,
        504,
        507,
        621,
        623,
        625
      ]
    },
    {
      "num": "16",
      "slides": [
        563,
        565,
        567,
        573,
        575,
        577
      ]
    },
    {
      "num": "17",
      "slides": [
        307,
        310,
        313,
        341,
        344,
        347
      ]
    },
    {
      "num": "18",
      "slides": [
        733,
        735
      ]
    },
    {
      "num": "19",
      "slides": [
        271,
        274,
        277,
        501,
        504,
        507
      ]
    },
    {
      "num": "20",
      "slides": [
        543,
        545,
        547,
        621,
        623,
        625
      ]
    },
    {
      "num": "21",
      "slides": [
        543,
        545,
        547
      ]
    },
    {
      "num": "22",
      "slides": [
        641,
        644,
        645,
        647,
        649,
        651
      ]
    }
  ],
  "practice-exam-9.md": [
    {
      "num": "1",
      "slides": [
        42,
        44,
        47
      ]
    },
    {
      "num": "2",
      "slides": [
        42,
        44,
        47,
        156,
        160
      ]
    },
    {
      "num": "3",
      "slides": [
        42,
        44,
        47,
        156,
        160
      ]
    },
    {
      "num": "4",
      "slides": [
        42,
        44,
        47,
        156,
        160
      ]
    },
    {
      "num": "5",
      "slides": [
        42,
        44,
        47
      ]
    },
    {
      "num": "6",
      "slides": [
        42,
        44,
        47,
        156,
        160
      ]
    },
    {
      "num": "7",
      "slides": [
        50,
        51,
        56,
        57,
        59
      ]
    },
    {
      "num": "8",
      "slides": [
        32,
        35,
        38,
        66,
        68,
        70
      ]
    },
    {
      "num": "9",
      "slides": [
        66,
        68,
        70
      ]
    },
    {
      "num": "10",
      "slides": [
        100,
        103,
        106,
        112,
        115,
        621
      ]
    },
    {
      "num": "11",
      "slides": [
        100,
        103,
        106,
        621,
        623,
        625
      ]
    },
    {
      "num": "12",
      "slides": [
        50,
        51,
        100,
        103,
        106,
        112
      ]
    },
    {
      "num": "13",
      "slides": [
        82,
        85,
        88,
        100,
        103,
        106
      ]
    },
    {
      "num": "14",
      "slides": [
        50,
        51,
        132,
        136
      ]
    },
    {
      "num": "15",
      "slides": [
        50,
        51,
        144,
        148
      ]
    },
    {
      "num": "16",
      "slides": [
        156,
        160
      ]
    },
    {
      "num": "17",
      "slides": [
        196,
        200,
        204,
        549,
        551
      ]
    },
    {
      "num": "18",
      "slides": [
        200,
        204,
        208,
        355,
        357,
        359
      ]
    },
    {
      "num": "19",
      "slides": [
        200,
        204,
        208,
        212,
        216,
        355
      ]
    },
    {
      "num": "20",
      "slides": [
        32,
        35,
        38,
        42,
        44,
        47
      ]
    }
  ]
}